lmnotify/__init__.py
lmnotify/config.py
lmnotify/const.py
lmnotify/lmnotify.py
lmnotify/models.py
lmnotify/session.py
lmnotify/ssdp.py
lmnotify-0.0.6.dist-info/DESCRIPTION.rst
lmnotify-0.0.6.dist-info/METADATA
lmnotify-0.0.6.dist-info/RECORD
lmnotify-0.0.6.dist-info/WHEEL
lmnotify-0.0.6.dist-info/metadata.json
lmnotify-0.0.6.dist-info/top_level.txt
