Metadata-Version: 2.0
Name: lmnotify
Version: 0.0.6
Summary: A package for sending notifications to LaMetric Time.
Home-page: https://github.com/keans/lmnotify
Author: Ansgar Kellner
Author-email: keans@gmx.de
License: MIT
Keywords: LaMetric notification
Platform: UNKNOWN
Classifier: Development Status :: 3 - Alpha
Classifier: Intended Audience :: Developers
Classifier: Topic :: Software Development :: Build Tools
Classifier: License :: OSI Approved :: MIT License
Classifier: Programming Language :: Python :: 2
Classifier: Programming Language :: Python :: 2.6
Classifier: Programming Language :: Python :: 2.7
Classifier: Programming Language :: Python :: 3
Classifier: Programming Language :: Python :: 3.3
Classifier: Programming Language :: Python :: 3.4
Classifier: Programming Language :: Python :: 3.5
Classifier: Programming Language :: Python :: 3.6
Requires-Dist: requests
Requires-Dist: oauthlib
Requires-Dist: requests-oauthlib
